pyunpack/__init__.py
pyunpack/about.py
pyunpack/cli.py
pyunpack/py.typed
pyunpack-0.3.dist-info/LICENSE.txt
pyunpack-0.3.dist-info/METADATA
pyunpack-0.3.dist-info/WHEEL
pyunpack-0.3.dist-info/top_level.txt
pyunpack-0.3.dist-info/RECORD
